{
  "content": [
    {
      "content": null,
      "created": "2022-08-28T01:02:56.811118Z",
      "format": null,
      "last_modified": "2022-08-28T01:02:56.811118Z",
      "mimetype": null,
      "name": "jupyterlite",
      "path": "posts/2022/jupyterlite",
      "size": null,
      "type": "directory",
      "writable": true
    }
  ],
  "created": "2022-08-28T00:46:03.920259Z",
  "format": "json",
  "last_modified": "2022-08-28T00:46:03.920259Z",
  "mimetype": null,
  "name": "2022",
  "path": "posts/2022",
  "size": null,
  "type": "directory",
  "writable": true
}